pyclustertend/__init__.py
pyclustertend/hopkins.py
pyclustertend/metric.py
pyclustertend/visual_assessment_of_tendency.py
pyclustertend-1.8.2.dist-info/LICENSE
pyclustertend-1.8.2.dist-info/WHEEL
pyclustertend-1.8.2.dist-info/METADATA
pyclustertend-1.8.2.dist-info/RECORD
