Metadata-Version: 2.1
Name: pyclustertend
Version: 1.8.2
Summary: A package to assess cluster tendency for unsupervised learning
Home-page: https://github.com/lachhebo/pyclustertend
License: BSD-3-Clause
Keywords: cluster tendency,clustering,machine learning,hopkins,VAT
Author: Ismaïl Lachheb
Requires-Python: >=3.8,<3.10
Classifier: License :: OSI Approved :: BSD License
Classifier: Programming Language :: Python :: 3
Classifier: Programming Language :: Python :: 3.8
Classifier: Programming Language :: Python :: 3.9
Requires-Dist: matplotlib (>=3.3.3,<4.0.0)
Requires-Dist: numba (>=0.54.1,<0.55.0)
Requires-Dist: numpy (==1.20.3)
Requires-Dist: pandas (>=1.2.0,<2.0.0)
Requires-Dist: scikit-learn (>=1.1.2,<2.0.0)
Project-URL: Documentation, https://pyclustertend.readthedocs.io/en/master/
Project-URL: Repository, https://github.com/lachhebo/pyclustertend
